app/__init__.py
app/agent.py
app/config.example.py
app/config.py
app/http_mcp_server.py
app/main.py
app/mcp_server.py
app/loaders/__init__.py
app/loaders/my_api_loader.py
mcp_servicenex-0.1.3.dist-info/METADATA
mcp_servicenex-0.1.3.dist-info/WHEEL
mcp_servicenex-0.1.3.dist-info/entry_points.txt
mcp_servicenex-0.1.3.dist-info/top_level.txt
mcp_servicenex-0.1.3.dist-info/RECORD
