Metadata-Version: 2.4
Name: mcp-servicenex
Version: 0.1.3
Summary: A Model Context Protocol (MCP) server for ServiceNex knowledge base articles and support tickets
Author-email: banusoppan <banu.soppan@ivedha.com>
License: MIT
Project-URL: Homepage, https://github.com/ivedha-tech/servicenex-mcp-server
Project-URL: Documentation, https://github.com/ivedha-tech/servicenex-mcp-server#readme
Project-URL: Repository, https://github.com/ivedha-tech/servicenex-mcp-server
Project-URL: Issues, https://github.com/ivedha-tech/servicenex-mcp-server/issues
Keywords: mcp,servicenex,model-context-protocol,ai,claude
Classifier: Development Status :: 4 - Beta
Classifier: Intended Audience :: Developers
Classifier: License :: OSI Approved :: MIT License
Classifier: Programming Language :: Python :: 3
Classifier: Programming Language :: Python :: 3.10
Classifier: Programming Language :: Python :: 3.11
Classifier: Programming Language :: Python :: 3.12
Classifier: Topic :: Software Development :: Libraries :: Python Modules
Classifier: Topic :: Internet :: WWW/HTTP :: Dynamic Content
Requires-Python: >=3.10
Requires-Dist: mcp>=1.0.0
Requires-Dist: requests>=2.31.0
Requires-Dist: fastapi>=0.116.1
Requires-Dist: uvicorn>=0.35.0
Provides-Extra: dev
Requires-Dist: pytest>=7.0.0; extra == "dev"
Requires-Dist: pytest-asyncio>=0.21.0; extra == "dev"
Requires-Dist: black>=23.0.0; extra == "dev"
Requires-Dist: ruff>=0.9.0; extra == "dev"
